mcp_nix/__init__.py
mcp_nix/cache.py
mcp_nix/homemanager.py
mcp_nix/models.py
mcp_nix/nix_nomad.py
mcp_nix/nixhub.py
mcp_nix/noogle.py
mcp_nix/nuschtos.py
mcp_nix/options.py
mcp_nix/search.py
mcp_nix/sources.py
mcp_nix/tools.py
mcp_nix/utils.py
mcp_nix-0.4.0.dist-info/METADATA
mcp_nix-0.4.0.dist-info/WHEEL
mcp_nix-0.4.0.dist-info/entry_points.txt
mcp_nix-0.4.0.dist-info/licenses/LICENSE
mcp_nix-0.4.0.dist-info/RECORD
