Metadata-Version: 2.4
Name: mcp-nix
Version: 0.4.0
Summary: MCP server for Nixpkgs, NixOS and Home Manager
Project-URL: Homepage, https://github.com/felixdorn/mcp-nix
Project-URL: Repository, https://github.com/felixdorn/mcp-nix
Project-URL: Issues, https://github.com/felixdorn/mcp-nix/issues
Author-email: Félix Dorn <dorn@xfe.li>
License-Expression: GPL-3.0-or-later
License-File: LICENSE
Keywords: ai,claude,home-manager,llm,mcp,model-context-protocol,nix,nixos
Classifier: Development Status :: 4 - Beta
Classifier: Environment :: Console
Classifier: Intended Audience :: Developers
Classifier: License :: OSI Approved :: GNU General Public License v3 or later (GPLv3+)
Classifier: Operating System :: OS Independent
Classifier: Programming Language :: Python :: 3.13
Requires-Python: >=3.13
Requires-Dist: beautifulsoup4>=4.12.0
Requires-Dist: diskcache>=5.6.0
Requires-Dist: fastmcp>=0.1.0
Requires-Dist: lunr>=0.7.0
Requires-Dist: pydantic>=2.0.0
Requires-Dist: pyixx
Requires-Dist: pyyaml>=6.0.0
Requires-Dist: requests>=2.31.0
Requires-Dist: wasmtime>=23.0.0
